autogrammer/Autogrammer.py
autogrammer/__init__.py
autogrammer-0.0.1.dist-info/LICENSE
autogrammer-0.0.1.dist-info/METADATA
autogrammer-0.0.1.dist-info/WHEEL
autogrammer-0.0.1.dist-info/top_level.txt
autogrammer-0.0.1.dist-info/RECORD
