Metadata-Version: 2.1
Name: autogrammer
Version: 0.0.1
Summary: A library for generating syntactically valid code from an LLM.
Author-email: Kevin Scott <kevin@autogrammer.dev>
Project-URL: Homepage, https://github.com/thekevinscott/autogrammer
Project-URL: Bug Tracker, https://github.com/thekevinscott/autogrammer/issues
Classifier: Programming Language :: Python :: 3
Classifier: License :: OSI Approved :: MIT License
Classifier: Operating System :: OS Independent
Requires-Python: >=3.10
License-File: LICENSE
